{
  "posts": [
    {
      "id": 2,
      "firstName": "deniz",
      "lastName": "kabaçelik",
      "email": "dkabacelik96@gmail.com",
      "mobile": "4",
      "salary": "5"
    },
    {
      "id": 3,
      "firstName": "Gökay",
      "lastName": "Öztürk",
      "email": "gokay@gmail.com",
      "mobile": "40",
      "salary": "40"
    },
    {
      "id": 4,
      "firstName": "s",
      "lastName": "sewqwe",
      "email": "s@gmail.com",
      "mobile": "53",
      "salary": "5444"
    },
    {
      "id": 6,
      "firstName": "deniz",
      "lastName": "kabaçelik",
      "email": "d@gmail.com",
      "mobile": "3",
      "salary": "3"
    },
    {
      "id": 7,
      "firstName": "dsfdsf",
      "lastName": "sdas",
      "email": "sdsad",
      "mobile": "1",
      "salary": "1"
    },
    {
      "id": 8,
      "firstName": "q",
      "lastName": "w",
      "email": "ds",
      "mobile": "5",
      "salary": "5"
    },
    {
      "id": 9,
      "firstName": "s",
      "lastName": "s",
      "email": "dsds@gmail.com",
      "mobile": "13",
      "salary": "13"
    }
  ],
  "signupUsers": [
    {
      "fullname": "Deniz Kabaçelik",
      "email": "admin",
      "password": "Adm1234",
      "mobile": 5530138743,
      "id": 1
    }
  ],
  "profile": {
    "name": "typicode"
  }
}